litestar_htmx/__init__.py
litestar_htmx/__metadata__.py
litestar_htmx/_utils.py
litestar_htmx/plugin.py
litestar_htmx/py.typed
litestar_htmx/request.py
litestar_htmx/response.py
litestar_htmx/types.py
litestar_htmx-0.4.0.dist-info/METADATA
litestar_htmx-0.4.0.dist-info/WHEEL
litestar_htmx-0.4.0.dist-info/licenses/LICENSE
litestar_htmx-0.4.0.dist-info/RECORD
