Metadata-Version: 2.3
Name: litestar-htmx
Version: 0.4.0
Summary: HTMX Integration for Litesstar
Author-email: Cody Fincher <cody@litestar.dev>
Maintainer-email: Litestar Developers <hello@litestar.dev>, Cody Fincher <cody@litestar.dev>, Jacob Coffee <jacob@litestar.dev>, Janek Nouvertné <provinzkraut@litestar.dev>, Visakh Unnikrishnan <guacs@litestar.dev>, Alc <alc@litestar.dev>
Requires-Python: <4.0,>=3.8
